<?xml version="1.0" encoding="UTF-8" standalone="yes"?><p:sld xmlns:a="http://schemas.openxmlformats.org/drawingml/2006/main" xmlns:r="http://schemas.openxmlformats.org/officeDocument/2006/relationships" xmlns:mc="http://schemas.openxmlformats.org/markup-compatibility/2006" xmlns:mv="urn:schemas-microsoft-com:mac:vml" xmlns:p="http://schemas.openxmlformats.org/presentationml/2006/main" xmlns:c="http://schemas.openxmlformats.org/drawingml/2006/chart" xmlns:dgm="http://schemas.openxmlformats.org/drawingml/2006/diagram" xmlns:o="urn:schemas-microsoft-com:office:office" xmlns:v="urn:schemas-microsoft-com:vml" xmlns:pvml="urn:schemas-microsoft-com:office:powerpoint" xmlns:com="http://schemas.openxmlformats.org/drawingml/2006/compatibility" xmlns:p14="http://schemas.microsoft.com/office/powerpoint/2010/main"><p:cSld><p:spTree><p:nvGrpSpPr><p:cNvPr id="86" name="Shape 86"/><p:cNvGrpSpPr/><p:nvPr/></p:nvGrpSpPr><p:grpSpPr><a:xfrm><a:off x="0" y="0"/><a:ext cx="0" cy="0"/><a:chOff x="0" y="0"/><a:chExt cx="0" cy="0"/></a:xfrm></p:grpSpPr><p:sp><p:nvSpPr><p:cNvPr id="87" name="Shape 87"/><p:cNvSpPr txBox="1"/><p:nvPr><p:ph idx="1" type="body"/></p:nvPr></p:nvSpPr><p:spPr><a:xfrm rot="-125183"><a:off x="255328" y="1216482"/><a:ext cx="8520548" cy="3099853"/></a:xfrm><a:prstGeom prst="rect"><a:avLst/></a:prstGeom><a:solidFill><a:srgbClr val="FCC028"><a:alpha val="88690"/></a:srgbClr></a:solidFill></p:spPr><p:txBody><a:bodyPr anchorCtr="0" anchor="t" bIns="91425" lIns="91425" rIns="91425" tIns="91425"><a:noAutofit/></a:bodyPr><a:lstStyle/><a:p><a:pPr indent="-419100" lvl="0" marL="457200" rtl="0"><a:spcBef><a:spcPts val="0"/></a:spcBef><a:spcAft><a:spcPts val="0"/></a:spcAft><a:buClr><a:srgbClr val="000000"/></a:buClr><a:buSzPct val="100000"/><a:buFont typeface="Comic Sans MS"/><a:buChar char="●"/></a:pPr><a:r><a:rPr lang="en" sz="3000"><a:solidFill><a:srgbClr val="000000"/></a:solidFill><a:latin typeface="Comic Sans MS"/><a:ea typeface="Comic Sans MS"/><a:cs typeface="Comic Sans MS"/><a:sym typeface="Comic Sans MS"/></a:rPr><a:t>App til gruppesamtaler i team (Oppg 1)</a:t></a:r></a:p><a:p><a:pPr indent="-228600" lvl="0" marL="457200" rtl="0"><a:spcBef><a:spcPts val="0"/></a:spcBef><a:spcAft><a:spcPts val="0"/></a:spcAft><a:buClr><a:srgbClr val="000000"/></a:buClr><a:buFont typeface="Comic Sans MS"/><a:buChar char="●"/></a:pPr><a:r><a:rPr lang="en"><a:solidFill><a:srgbClr val="000000"/></a:solidFill><a:latin typeface="Comic Sans MS"/><a:ea typeface="Comic Sans MS"/><a:cs typeface="Comic Sans MS"/><a:sym typeface="Comic Sans MS"/></a:rPr><a:t>Basisfunksjonaliteter:</a:t></a:r></a:p><a:p><a:pPr indent="-342900" lvl="1" marL="914400" rtl="0"><a:spcBef><a:spcPts val="0"/></a:spcBef><a:spcAft><a:spcPts val="0"/></a:spcAft><a:buClr><a:srgbClr val="000000"/></a:buClr><a:buSzPct val="100000"/><a:buFont typeface="Comic Sans MS"/><a:buChar char="○"/></a:pPr><a:r><a:rPr lang="en" sz="1800"><a:solidFill><a:srgbClr val="000000"/></a:solidFill><a:latin typeface="Comic Sans MS"/><a:ea typeface="Comic Sans MS"/><a:cs typeface="Comic Sans MS"/><a:sym typeface="Comic Sans MS"/></a:rPr><a:t>Team</a:t></a:r></a:p><a:p><a:pPr indent="-342900" lvl="1" marL="914400" rtl="0"><a:spcBef><a:spcPts val="0"/></a:spcBef><a:spcAft><a:spcPts val="0"/></a:spcAft><a:buClr><a:srgbClr val="000000"/></a:buClr><a:buSzPct val="100000"/><a:buFont typeface="Comic Sans MS"/><a:buChar char="○"/></a:pPr><a:r><a:rPr lang="en" sz="1800"><a:solidFill><a:srgbClr val="000000"/></a:solidFill><a:latin typeface="Comic Sans MS"/><a:ea typeface="Comic Sans MS"/><a:cs typeface="Comic Sans MS"/><a:sym typeface="Comic Sans MS"/></a:rPr><a:t>Kanaler</a:t></a:r></a:p><a:p><a:pPr indent="-342900" lvl="1" marL="914400" rtl="0"><a:spcBef><a:spcPts val="0"/></a:spcBef><a:spcAft><a:spcPts val="0"/></a:spcAft><a:buClr><a:srgbClr val="000000"/></a:buClr><a:buSzPct val="100000"/><a:buFont typeface="Comic Sans MS"/><a:buChar char="○"/></a:pPr><a:r><a:rPr lang="en" sz="1800"><a:solidFill><a:srgbClr val="000000"/></a:solidFill><a:latin typeface="Comic Sans MS"/><a:ea typeface="Comic Sans MS"/><a:cs typeface="Comic Sans MS"/><a:sym typeface="Comic Sans MS"/></a:rPr><a:t>Private samtaler</a:t></a:r></a:p><a:p><a:pPr indent="-342900" lvl="1" marL="914400" rtl="0"><a:spcBef><a:spcPts val="0"/></a:spcBef><a:spcAft><a:spcPts val="0"/></a:spcAft><a:buClr><a:srgbClr val="000000"/></a:buClr><a:buSzPct val="100000"/><a:buFont typeface="Comic Sans MS"/><a:buChar char="○"/></a:pPr><a:r><a:rPr lang="en" sz="1800"><a:solidFill><a:srgbClr val="000000"/></a:solidFill><a:latin typeface="Comic Sans MS"/><a:ea typeface="Comic Sans MS"/><a:cs typeface="Comic Sans MS"/><a:sym typeface="Comic Sans MS"/></a:rPr><a:t>Mentions/Tagging</a:t></a:r></a:p><a:p><a:pPr indent="-342900" lvl="1" marL="914400" rtl="0"><a:spcBef><a:spcPts val="0"/></a:spcBef><a:spcAft><a:spcPts val="0"/></a:spcAft><a:buClr><a:srgbClr val="000000"/></a:buClr><a:buSzPct val="100000"/><a:buFont typeface="Comic Sans MS"/><a:buChar char="○"/></a:pPr><a:r><a:rPr lang="en" sz="1800"><a:solidFill><a:srgbClr val="000000"/></a:solidFill><a:latin typeface="Comic Sans MS"/><a:ea typeface="Comic Sans MS"/><a:cs typeface="Comic Sans MS"/><a:sym typeface="Comic Sans MS"/></a:rPr><a:t>Reactions</a:t></a:r></a:p><a:p><a:pPr indent="-342900" lvl="1" marL="914400" rtl="0"><a:spcBef><a:spcPts val="0"/></a:spcBef><a:spcAft><a:spcPts val="0"/></a:spcAft><a:buClr><a:srgbClr val="000000"/></a:buClr><a:buSzPct val="100000"/><a:buFont typeface="Comic Sans MS"/><a:buChar char="○"/></a:pPr><a:r><a:rPr lang="en" sz="1800"><a:solidFill><a:srgbClr val="000000"/></a:solidFill><a:latin typeface="Comic Sans MS"/><a:ea typeface="Comic Sans MS"/><a:cs typeface="Comic Sans MS"/><a:sym typeface="Comic Sans MS"/></a:rPr><a:t>Fildeling</a:t></a:r></a:p><a:p><a:pPr lvl="0" rtl="0"><a:spcBef><a:spcPts val="0"/></a:spcBef><a:spcAft><a:spcPts val="0"/></a:spcAft><a:buNone/></a:pPr><a:r><a:t></a:t></a:r><a:endParaRPr sz="1100"><a:solidFill><a:srgbClr val="000000"/></a:solidFill><a:latin typeface="Arial"/><a:ea typeface="Arial"/><a:cs typeface="Arial"/><a:sym typeface="Arial"/></a:endParaRPr></a:p></p:txBody></p:sp><p:pic><p:nvPicPr><p:cNvPr id="88" name="Shape 88"/><p:cNvPicPr preferRelativeResize="0"/><p:nvPr/></p:nvPicPr><p:blipFill><a:blip r:embed="rId3"><a:alphaModFix/></a:blip><a:stretch><a:fillRect/></a:stretch></p:blipFill><p:spPr><a:xfrm><a:off x="311700" y="110471"/><a:ext cx="2725825" cy="1090325"/></a:xfrm><a:prstGeom prst="rect"><a:avLst/></a:prstGeom><a:noFill/><a:ln><a:noFill/></a:ln></p:spPr></p:pic></p:spTree></p:cSld><p:clrMapOvr><a:masterClrMapping/></p:clrMapOvr></p:sld>